tokubackup.py
autotokubackup-1.2.dist-info/DESCRIPTION.rst
autotokubackup-1.2.dist-info/METADATA
autotokubackup-1.2.dist-info/RECORD
autotokubackup-1.2.dist-info/WHEEL
autotokubackup-1.2.dist-info/entry_points.txt
autotokubackup-1.2.dist-info/metadata.json
autotokubackup-1.2.dist-info/top_level.txt
backup/__init__.py
backup/backup_calculation.py
etc/tokubackup.conf
general_conf/__init__.py
general_conf/generalops.py
