Metadata-Version: 2.0
Name: autotokubackup
Version: 1.2
Summary: Commandline tool written in Python3 for using Percona TokuBackup
Home-page: https://github.com/Percona-Lab/autotokubackup
Author: Shahriyar Rzayev
Author-email: shahriyar.rzayev@percona.com
License: GPL
Download-URL: https://github.com/Percona-Lab/autotokubackup/archive/v1.2.tar.gz
Platform: UNKNOWN
Requires-Dist: click (>=3.3)
Requires-Dist: mysql-connector (>=2.0.2)
Requires-Dist: watchdog (>=0.8.3)
